rebase/__init__.py
rebase/core/__init__.py
rebase/core/model.py
rebase/core/object.py
rebase/core/validator.py
rebase/validators/__init__.py
rebase/validators/alnum_validator.py
rebase/validators/bool_validator.py
rebase/validators/integer_validator.py
rebase/validators/nested_validator.py
rebase/validators/range_validator.py
rebase/validators/string_validator.py
rebase-1.3.2.dist-info/LICENSE
rebase-1.3.2.dist-info/METADATA
rebase-1.3.2.dist-info/WHEEL
rebase-1.3.2.dist-info/top_level.txt
rebase-1.3.2.dist-info/RECORD
