Metadata-Version: 2.1
Name: rebase
Version: 1.3.2
Summary: UNKNOWN
Home-page: UNKNOWN
Author: Yuv Joodhisty
Author-email: locustv2@gmail.com
Maintainer: Yuv Joodhisty
Maintainer-email: locustv2@gmail.com
License: UNKNOWN
Platform: UNKNOWN
Classifier: Programming Language :: Python :: 3
Classifier: Operating System :: OS Independent
Requires-Python: >=3.6
Requires-Dist: simplejson
